techlens_pygments_tsx/__init__.py
techlens_pygments_tsx/tsx.py
techlens_pygments_tsx-0.3.0.dist-info/METADATA
techlens_pygments_tsx-0.3.0.dist-info/WHEEL
techlens_pygments_tsx-0.3.0.dist-info/licenses/LICENSE
techlens_pygments_tsx-0.3.0.dist-info/RECORD
