Metadata-Version: 2.4
Name: techlens-pygments-tsx
Version: 0.3.0
Summary: A plugin for adding TSX support to Pygments based off the work of the JSX plugin.
Project-URL: Homepage, https://www.crosslaketech.com/
Author-email: Crosslake Technologies <techlens@crosslaketech.com>
License-Expression: CC-BY-NC-ND-4.0
License-File: LICENSE
Classifier: Development Status :: 5 - Production/Stable
Classifier: Operating System :: OS Independent
Classifier: Programming Language :: JavaScript
Classifier: Programming Language :: Python :: 3
Classifier: Topic :: Software Development
Classifier: Topic :: Text Editors
Requires-Python: >=3.10
Requires-Dist: flake8
Requires-Dist: jsx-lexer==2.0.1
Requires-Dist: pygments==2.19.2
Requires-Dist: pytest
Requires-Dist: pytest-cov
